{"__license":"This file has been derived from Unicode Common Locale Data Repository (CLDR) files (http://cldr.unicode.org). See the copyright and permission notice in the Unicode-Data-Files-LICENSE.txt available at the same location as this file or visit http://www.unicode.org/copyright.html","languages":{"aa":"Tiếng Afar","ab":"Tiếng Abkhazia","ace":"Tiếng Achinese","ach":"Tiếng Acoli","ada":"Tiếng Adangme","ady":"Tiếng Adyghe","ae":"Tiếng Avestan","aeb":"aeb","af":"Tiếng Nam Phi","afh":"Tiếng Afrihili","agq":"Tiếng Aghem","ain":"Tiếng Ainu","ak":"Tiếng Akan","akk":"Tiếng Akkadia","akz":"akz","ale":"Tiếng Aleut","aln":"aln","alt":"Tiếng Altai Miền Nam","am":"Tiếng Amharic","an":"Tiếng Aragon","ang":"Tiếng Anh cổ","anp":"Tiếng Angika","ar":"Tiếng Ả Rập","ar_001":"Tiếng Ả Rập Hiện đại","arc":"Tiếng Aramaic","arn":"Tiếng Araucanian","aro":"aro","arp":"Tiếng Arapaho","arq":"arq","arw":"Tiếng Arawak","ary":"ary","arz":"arz","as":"Tiếng Assam","asa":"Tiếng Asu","ase":"ase","ast":"Tiếng Asturias","av":"Tiếng Avaric","avk":"avk","awa":"Tiếng Awadhi","ay":"Tiếng Aymara","az":"Tiếng Azerbaijan","az_alt-short":"Tiếng Azeri","azb":"azb","ba":"Tiếng Bashkir","bal":"Tiếng Baluchi","ban":"Tiếng Bali","bar":"bar","bas":"Tiếng Basaa","bax":"Tiếng Bamun","bbc":"bbc","bbj":"Tiếng Ghomala","be":"Tiếng Belarus","bej":"Tiếng Beja","bem":"Tiếng Bemba","bew":"bew","bez":"Tiếng Bena","bfd":"Tiếng Bafut","bfq":"bfq","bg":"Tiếng Bulgaria","bho":"Tiếng Bhojpuri","bi":"Tiếng Bislama","bik":"Tiếng Bikol","bin":"Tiếng Bini","bjn":"bjn","bkm":"Tiếng Kom","bla":"Tiếng Siksika","bm":"Tiếng Bambara","bn":"Tiếng Bengali","bo":"Tiếng Tây Tạng","bpy":"bpy","bqi":"bqi","br":"Tiếng Breton","bra":"Tiếng Braj","brh":"brh","brx":"Tiếng Bodo","bs":"Tiếng Nam Tư","bss":"Tiếng Akoose","bua":"Tiếng Buriat","bug":"Tiếng Bugin","bum":"Tiếng Bulu","byn":"Tiếng Blin","byv":"Tiếng Medumba","ca":"Tiếng Catalan","cad":"Tiếng Caddo","car":"Tiếng Carib","cay":"Tiếng Cayuga","cch":"Tiếng Atsam","ce":"Tiếng Chechen","ceb":"Tiếng Cebuano","cgg":"Tiếng Chiga","ch":"Tiếng Chamorro","chb":"Tiếng Chibcha","chg":"Tiếng Chagatai","chk":"Tiếng Chuuk","chm":"Tiếng Mari","chn":"Biệt ngữ Chinook","cho":"Tiếng Choctaw","chp":"Tiếng Chipewyan","chr":"Tiếng Cherokee","chy":"Tiếng Cheyenne","ckb":"Tiếng Kurd Sorani","co":"Tiếng Corsica","cop":"Tiếng Coptic","cps":"cps","cr":"Tiếng Cree","crh":"Tiếng Thổ Nhĩ Kỳ Crimean","cs":"Tiếng Séc","csb":"Tiếng Kashubia","cu":"Tiếng Slavơ Nhà thờ","cv":"Tiếng Chuvash","cy":"Tiếng Wales","da":"Tiếng Đan Mạch","dak":"Tiếng Dakota","dar":"Tiếng Dargwa","dav":"Tiếng Taita","de":"Tiếng Đức","de_AT":"de_AT","de_CH":"Tiếng Thượng Giéc-man (Thụy Sĩ)","del":"Tiếng Delaware","den":"Tiếng Slave","dgr":"Tiếng Dogrib","din":"Tiếng Dinka","dje":"Tiếng Zarma","doi":"Tiếng Dogri","dsb":"Tiếng Hạ Sorbia","dtp":"dtp","dua":"Tiếng Duala","dum":"Tiếng Hà Lan Trung cổ","dv":"Tiếng Divehi","dyo":"Tiếng Jola-Fonyi","dyu":"Tiếng Dyula","dz":"Tiếng Dzongkha","dzg":"Tiếng Dazaga","ebu":"Tiếng Embu","ee":"Tiếng Ewe","efi":"Tiếng Efik","egl":"egl","egy":"Tiếng Ai Cập cổ","eka":"Tiếng Ekajuk","el":"Tiếng Hy Lạp","elx":"Tiếng Elamite","en":"Tiếng Anh","en_AU":"en_AU","en_CA":"en_CA","en_GB":"Tiếng Anh (Anh)","en_GB-alt-short":"Tiếng Anh (Anh)","en_US":"Tiếng Anh (Mỹ)","en_US-alt-short":"Tiếng Anh (Mỹ)","enm":"Tiếng Anh Trung cổ","eo":"Tiếng Quốc Tế Ngữ","es":"Tiếng Tây Ban Nha","es_419":"Tiếng Tây Ban Nha (Mỹ La tinh)","es_ES":"es_ES","es_MX":"es_MX","esu":"esu","et":"Tiếng Estonia","eu":"Tiếng Basque","ewo":"Tiếng Ewondo","ext":"ext","fa":"Tiếng Ba Tư","fan":"Tiếng Fang","fat":"Tiếng Fanti","ff":"Tiếng Fulah","fi":"Tiếng Phần Lan","fil":"Tiếng Philipin","fit":"fit","fj":"Tiếng Fiji","fo":"Tiếng Faore","fon":"Tiếng Fon","fr":"Tiếng Pháp","fr_CA":"fr_CA","fr_CH":"fr_CH","frc":"frc","frm":"Tiếng Pháp Trung cổ","fro":"Tiếng Pháp cổ","frp":"frp","frr":"Tiếng Frisian Miền Bắc","frs":"Tiếng Frisian Miền Đông","fur":"Tiếng Friulian","fy":"Tiếng Frisia","ga":"Tiếng Ai-len","gaa":"Tiếng Ga","gag":"Tiếng Gagauz","gan":"gan","gay":"Tiếng Gayo","gba":"Tiếng Gbaya","gbz":"gbz","gd":"Tiếng Xentơ (Xcốt len)","gez":"Tiếng Geez","gil":"Tiếng Gilbert","gl":"Tiếng Galician","glk":"glk","gmh":"Tiếng Thượng Giéc-man Trung cổ","gn":"Tiếng Guarani","goh":"Tiếng Thượng Giéc-man cổ","gom":"gom","gon":"Tiếng Gondi","gor":"Tiếng Gorontalo","got":"Tiếng Gô-tích","grb":"Tiếng Grebo","grc":"Tiếng Hy Lạp cổ","gsw":"Tiếng Đức (Thụy Sĩ)","gu":"Tiếng Gujarati","guc":"guc","gur":"gur","guz":"Tiếng Gusii","gv":"Tiếng Manx","gwi":"Tiếng Gwichʼin","ha":"Tiếng Hausa","hai":"Tiếng Haida","hak":"hak","haw":"Tiếng Hawaii","he":"Tiếng Do Thái","hi":"Tiếng Hindi","hif":"hif","hil":"Tiếng Hiligaynon","hit":"Tiếng Hittite","hmn":"Tiếng Hmông","ho":"Tiếng Hiri Motu","hr":"Tiếng Croatia","hsb":"Tiếng Thượng Sorbia","hsn":"hsn","ht":"Tiếng Haiti","hu":"Tiếng Hungary","hup":"Tiếng Hupa","hy":"Tiếng Armenia","hz":"Tiếng Herero","ia":"Tiếng Khoa Học Quốc Tế","iba":"Tiếng Iban","ibb":"Tiếng Ibibio","id":"Tiếng Indonesia","ie":"Tiếng Interlingue","ig":"Tiếng Igbo","ii":"Tiếng Di Tứ Xuyên","ik":"Tiếng Inupiaq","ilo":"Tiếng Iloko","inh":"Tiếng Ingush","io":"Tiếng Ido","is":"Tiếng Iceland","it":"Tiếng Ý","iu":"Tiếng Inuktitut","izh":"izh","ja":"Tiếng Nhật","jam":"jam","jbo":"Tiếng Lojban","jgo":"Tiếng Ngomba","jmc":"Tiếng Machame","jpr":"Tiếng Judeo-Ba Tư","jrb":"Tiếng Judeo-Ả Rập","jut":"jut","jv":"Tiếng Java","ka":"Tiếng Gruzia","kaa":"Tiếng Kara-Kalpak","kab":"Tiếng Kabyle","kac":"Tiếng Kachin","kaj":"Tiếng Jju","kam":"Tiếng Kamba","kaw":"Tiếng Kawi","kbd":"Tiếng Kabardian","kbl":"Tiếng Kanembu","kcg":"Tiếng Tyap","kde":"Tiếng Makonde","kea":"Tiếng Kabuverdianu","ken":"ken","kfo":"Tiếng Koro","kg":"Tiếng Kongo","kgp":"kgp","kha":"Tiếng Khasi","kho":"Tiếng Khotan","khq":"Tiếng Koyra Chiini","khw":"khw","ki":"Tiếng Kikuyu","kiu":"kiu","kj":"Tiếng Kuanyama","kk":"Tiếng Kazakh","kkj":"Tiếng Kako","kl":"Tiếng Kalaallisut","kln":"Tiếng Kalenjin","km":"Tiếng Khơ-me","kmb":"Tiếng Kimbundu","kn":"Tiếng Kannada","ko":"Tiếng Hàn","koi":"Tiếng Komi-Permyak","kok":"Tiếng Konkani","kos":"Tiếng Kosrae","kpe":"Tiếng Kpelle","kr":"Tiếng Kanuri","krc":"Tiếng Karachay-Balkar","kri":"kri","krj":"krj","krl":"Tiếng Karelian","kru":"Tiếng Kurukh","ks":"Tiếng Kashmiri","ksb":"Tiếng Shambala","ksf":"Tiếng Bafia","ksh":"Tiếng Cologne","ku":"Tiếng Kurd","kum":"Tiếng Kumyk","kut":"Tiếng Kutenai","kv":"Tiếng Komi","kw":"Tiếng Cornwall","ky":"Tiếng Kyrgyz","la":"Tiếng La-tinh","lad":"Tiếng Ladino","lag":"Tiếng Langi","lah":"Tiếng Lahnda","lam":"Tiếng Lamba","lb":"Tiếng Luxembourg","lez":"Tiếng Lezghian","lfn":"lfn","lg":"Tiếng Ganda","li":"Tiếng Limburg","lij":"lij","liv":"liv","lkt":"Tiếng Lakota","lmo":"lmo","ln":"Tiếng Lingala","lo":"Tiếng Lào","lol":"Tiếng Mongo","loz":"Tiếng Lozi","lt":"Tiếng Lít-va","ltg":"ltg","lu":"Tiếng Luba-Katanga","lua":"Tiếng Luba-Lulua","lui":"Tiếng Luiseno","lun":"Tiếng Lunda","luo":"Tiếng Luo","lus":"Tiếng Lushai","luy":"Tiếng Luyia","lv":"Tiếng Latvia","lzh":"lzh","lzz":"lzz","mad":"Tiếng Madura","maf":"Tiếng Mafa","mag":"Tiếng Magahi","mai":"Tiếng Maithili","mak":"Tiếng Makasar","man":"Tiếng Mandingo","mas":"Tiếng Masai","mde":"Tiếng Maba","mdf":"Tiếng Moksha","mdr":"Tiếng Mandar","men":"Tiếng Mende","mer":"Tiếng Meru","mfe":"Tiếng Morisyen","mg":"Tiếng Malagasy","mga":"Tiếng Ai-len Trung cổ","mgh":"Tiếng Makhuwa-Meetto","mgo":"Tiếng Meta’","mh":"Tiếng Marshall","mi":"Tiếng Maori","mic":"Tiếng Micmac","min":"Tiếng Minangkabau","mk":"Tiếng Macedonia","ml":"Tiếng Malayalam","mn":"Tiếng Mông Cổ","mnc":"Tiếng Manchu","mni":"Tiếng Manipuri","moh":"Tiếng Mohawk","mos":"Tiếng Mossi","mr":"Tiếng Marathi","mrj":"mrj","ms":"Tiếng Malaysia","mt":"Tiếng Malt","mua":"Tiếng Mundang","mul":"Nhiều Ngôn ngữ","mus":"Tiếng Creek","mwl":"Tiếng Miranda","mwr":"Tiếng Marwari","mwv":"mwv","my":"Tiếng Miến Điện","mye":"Tiếng Myene","myv":"Tiếng Erzya","mzn":"mzn","na":"Tiếng Nauru","nan":"nan","nap":"Tiếng Napoli","naq":"Tiếng Nama","nb":"Tiếng Na Uy (Bokmål)","nd":"Tiếng Ndebele Miền Bắc","nds":"Tiếng Hạ Giéc-man","ne":"Tiếng Nepal","new":"Tiếng Newari","ng":"Tiếng Ndonga","nia":"Tiếng Nias","niu":"Tiếng Niuean","njo":"njo","nl":"Tiếng Hà Lan","nl_BE":"Tiếng Flemish","nmg":"Tiếng Kwasio","nn":"Tiếng Na Uy (Nynorsk)","nnh":"Tiếng Ngiemboon","no":"Tiếng Na Uy","nog":"Tiếng Nogai","non":"Tiếng Na Uy cổ","nov":"nov","nqo":"Tiếng N’Ko","nr":"Tiếng Ndebele Miền Nam","nso":"Bắc Sotho","nus":"Tiếng Nuer","nv":"Tiếng Navajo","nwc":"Tiếng Newari Cổ điển","ny":"Tiếng Nyanja","nym":"Tiếng Nyamwezi","nyn":"Tiếng Nyankole","nyo":"Tiếng Nyoro","nzi":"Tiếng Nzima","oc":"Tiếng Occitan","oj":"Tiếng Ojibwa","om":"Tiếng Oromo","or":"Tiếng Oriya","os":"Tiếng Ossetic","osa":"Tiếng Osage","ota":"Tiếng Thổ Nhĩ Kỳ Ottoman","pa":"Tiếng Punjab","pag":"Tiếng Pangasinan","pal":"Tiếng Pahlavi","pam":"Tiếng Pampanga","pap":"Tiếng Papiamento","pau":"Tiếng Palauan","pcd":"pcd","pdc":"pdc","pdt":"pdt","peo":"Tiếng Ba Tư cổ","pfl":"pfl","phn":"Tiếng Phoenicia","pi":"Tiếng Pali","pl":"Tiếng Ba Lan","pms":"pms","pnt":"pnt","pon":"Tiếng Pohnpeian","prg":"prg","pro":"Tiếng Provençal cổ","ps":"Tiếng Pashto","ps_alt-variant":"Tiếng Pushto","pt":"Tiếng Bồ Đào Nha","pt_BR":"Tiếng Bồ Đào Nha (Braxin)","pt_PT":"pt_PT","qu":"Tiếng Quechua","quc":"Tiếng Kʼicheʼ","qug":"qug","raj":"Tiếng Rajasthani","rap":"Tiếng Rapanui","rar":"Tiếng Rarotongan","rgn":"rgn","rif":"rif","rm":"Tiếng Romansh","rn":"Tiếng Rundi","ro":"Tiếng Rumani","ro_MD":"Tiếng Moldova","rof":"Tiếng Rombo","rom":"Tiếng Romany","root":"Tiếng Root","rtm":"rtm","ru":"Tiếng Nga","rue":"rue","rug":"rug","rup":"Tiếng Aromania","rw":"Tiếng Kinyarwanda","rwk":"Tiếng Rwa","sa":"Tiếng Phạn","sad":"Tiếng Sandawe","sah":"Tiếng Sakha","sam":"Tiếng Samaritan Aramaic","saq":"Tiếng Samburu","sas":"Tiếng Sasak","sat":"Tiếng Santali","saz":"saz","sba":"Tiếng Ngambay","sbp":"Tiếng Sangu","sc":"Tiếng Sardinia","scn":"Tiếng Sicilia","sco":"Tiếng Scots","sd":"Tiếng Sindhi","sdc":"sdc","se":"Tiếng Sami Miền Bắc","see":"Tiếng Seneca","seh":"Tiếng Sena","sei":"sei","sel":"Tiếng Selkup","ses":"Tiếng Koyraboro Senni","sg":"Tiếng Sango","sga":"Tiếng Ai-len cổ","sgs":"sgs","sh":"Tiếng Xéc bi - Croatia","shi":"Tiếng Tachelhit","shn":"Tiếng Shan","shu":"Tiếng Ả-Rập Chad","si":"Tiếng Sinhala","sid":"Tiếng Sidamo","sk":"Tiếng Slovak","sl":"Tiếng Slovenia","sli":"sli","sly":"sly","sm":"Tiếng Samoa","sma":"TIếng Sami Miền Nam","smj":"Tiếng Lule Sami","smn":"Tiếng Inari Sami","sms":"Tiếng Skolt Sami","sn":"Tiếng Shona","snk":"Tiếng Soninke","so":"Tiếng Somali","sog":"Tiếng Sogdien","sq":"Tiếng An-ba-ni","sr":"Tiếng Serbia","srn":"Tiếng Sranan Tongo","srr":"Tiếng Serer","ss":"Tiếng Swati","ssy":"Tiếng Saho","st":"Tiếng Sesotho","stq":"stq","su":"Tiếng Sudan","suk":"Tiếng Sukuma","sus":"Tiếng Susu","sux":"Tiếng Sumeria","sv":"Tiếng Thụy Điển","sw":"Tiếng Swahili","swb":"Tiếng Cômo","swc":"Tiếng Swahili Congo","syc":"Tiếng Syria Cổ điển","syr":"Tiếng Syriac","szl":"szl","ta":"Tiếng Tamil","tcy":"tcy","te":"Tiếng Telugu","tem":"Tiếng Timne","teo":"Tiếng Teso","ter":"Tiếng Tereno","tet":"Tetum","tg":"Tiếng Tajik","th":"Tiếng Thái","ti":"Tiếng Tigrigya","tig":"Tiếng Tigre","tiv":"Tiếng Tiv","tk":"Tiếng Turk","tkl":"Tiếng Tokelau","tkr":"tkr","tl":"Tiếng Tagalog","tlh":"Tiếng Klingon","tli":"Tiếng Tlingit","tly":"tly","tmh":"Tiếng Tamashek","tn":"Tiếng Tswana","to":"Tiếng Tonga","tog":"Tiếng Nyasa Tonga","tpi":"Tiếng Tok Pisin","tr":"Tiếng Thổ Nhĩ Kỳ","tru":"tru","trv":"Tiếng Taroko","ts":"Tiếng Tsonga","tsd":"tsd","tsi":"Tiếng Tsimshian","tt":"Tiếng Tatar","ttt":"ttt","tum":"Tiếng Tumbuka","tvl":"Tiếng Tuvalu","tw":"Tiếng Twi","twq":"Tiếng Tasawaq","ty":"Tiếng Tahiti","tyv":"Tiếng Tuvinian","tzm":"Tiếng Tamazight Miền Trung Ma-rốc","udm":"Tiếng Udmurt","ug":"Tiếng Uyghur","uga":"Tiếng Ugaritic","uk":"Tiếng Ucraina","umb":"Tiếng Umbundu","und":"Ngôn ngữ không xác định","ur":"Tiếng Uđu","uz":"Tiếng Uzbek","vai":"Tiếng Vai","ve":"Tiếng Venda","vec":"vec","vep":"vep","vi":"Tiếng Việt","vls":"vls","vmf":"vmf","vo":"Tiếng Volapük","vot":"Tiếng Votic","vro":"vro","vun":"Tiếng Vunjo","wa":"Tiếng Walloon","wae":"Tiếng Walser","wal":"Tiếng Walamo","war":"Tiếng Waray","was":"Tiếng Washo","wo":"Tiếng Wolof","wuu":"wuu","xal":"Tiếng Kalmyk","xh":"Tiếng Xhosa","xmf":"xmf","xog":"Tiếng Soga","yao":"Tiếng Yao","yap":"Tiếng Yap","yav":"Tiếng Yangben","ybb":"Tiếng Yemba","yi":"Tiếng Y-đit","yo":"Tiếng Yoruba","yrl":"yrl","yue":"Tiếng Quảng Đông","za":"Tiếng Zhuang","zap":"Tiếng Zapotec","zbl":"Ký hiệu Blissymbols","zea":"zea","zen":"Tiếng Zenaga","zgh":"Tiếng Tamazight Chuẩn của Ma-rốc","zh":"Tiếng Trung","zh_Hans":"zh_Hans","zh_Hant":"zh_Hant","zu":"Tiếng Zulu","zun":"Tiếng Zuni","zxx":"Không có nội dung ngôn ngữ","zza":"Tiếng Zaza"},"scripts":{"Afak":"Chữ Afaka","Aghb":"Aghb","Arab":"Chữ Ả Rập","Arab-alt-variant":"Chữ Ba Tư-Ả Rập","Armi":"Chữ Imperial Aramaic","Armn":"Chữ Armenia","Avst":"Chữ Avestan","Bali":"Chữ Bali","Bamu":"Chữ Bamum","Bass":"Chữ Bassa Vah","Batk":"Chữ Batak","Beng":"Chữ Bengali","Blis":"Chữ Blissymbols","Bopo":"Chữ Bopomofo","Brah":"Chữ Brahmi","Brai":"Chữ nổi Braille","Bugi":"Chữ Bugin","Buhd":"Chữ Buhid","Cakm":"Chữ Chakma","Cans":"Âm tiết Thổ dân Canada Hợp nhất","Cari":"Chữ Caria","Cham":"Chữ Chăm","Cher":"Chữ Cherokee","Cirt":"Chữ Cirth","Copt":"Chữ Coptic","Cprt":"Chứ Síp","Cyrl":"Chữ Kirin","Cyrs":"Chữ Kirin Slavơ Nhà thờ cổ","Deva":"Chữ Devanagari","Dsrt":"Chữ Deseret","Dupl":"Chữ tốc ký Duployan","Egyd":"Chữ Ai Cập bình dân","Egyh":"Chữ Ai Cập thày tu","Egyp":"Chữ tượng hình Ai Cập","Elba":"Elba","Ethi":"Chữ Ethiopia","Geok":"Chữ Khutsuri Georgia","Geor":"Chữ Gruzia","Glag":"Chữ Glagolitic","Goth":"Chữ Gô-tích","Gran":"Chữ Grantha","Grek":"Chữ Hy Lạp","Gujr":"Chữ Gujarati","Guru":"Chữ Gurmukhi","Hang":"Chữ Hangul","Hani":"Chữ Hán","Hano":"Chữ Hanunoo","Hans":"Giản thể","Hans-alt-stand-alone":"Chữ Hán giản thể","Hant":"Phồn thể","Hant-alt-stand-alone":"Chữ Hán phồn thể","Hebr":"Chữ Do Thái","Hira":"Chữ Hiragana","Hluw":"Chữ tượng hình Anatolia","Hmng":"Chữ Pahawh Hmong","Hrkt":"Bảng ký hiệu âm tiết Tiếng Nhật","Hung":"Chữ Hungary cổ","Inds":"Chữ Indus","Ital":"Chữ Italic cổ","Java":"Chữ Java","Jpan":"Chữ Nhật Bản","Jurc":"Chữ Jurchen","Kali":"Chữ Kayah Li","Kana":"Chữ Katakana","Khar":"Chữ Kharoshthi","Khmr":"Chữ Khơ-me","Khoj":"Chữ Khojki","Knda":"Chữ Kannada","Kore":"Chữ Hàn Quốc","Kpel":"Chữ Kpelle","Kthi":"Chữ Kaithi","Lana":"Chữ Lanna","Laoo":"Chữ Lào","Latf":"Chữ La-tinh Fraktur","Latg":"Chữ La-tinh Xcốt-len","Latn":"Chữ La tinh","Lepc":"Chữ Lepcha","Limb":"Chữ Limbu","Lina":"Chữ Linear A","Linb":"Chữ Linear B","Lisu":"Chữ Fraser","Loma":"Chữ Loma","Lyci":"Chữ Lycia","Lydi":"Chữ Lydia","Mahj":"Mahj","Mand":"Chữ Mandaean","Mani":"Chữ Manichaean","Maya":"Chữ tượng hình Maya","Mend":"Chữ Mende","Merc":"Chữ Meroitic Nét thảo","Mero":"Chữ Meroitic","Mlym":"Chữ Malayalam","Modi":"Modi","Mong":"Chữ Mông Cổ","Moon":"Chữ nổi Moon","Mroo":"Chữ Mro","Mtei":"Chữ Meitei Mayek","Mymr":"Myanma","Narb":"Chữ Bắc Ả Rập cổ","Nbat":"Chữ Nabataean","Nkgb":"Chữ Naxi Geba","Nkoo":"Chữ N’Ko","Nshu":"Chữ Nüshu","Ogam":"Chữ Ogham","Olck":"Chữ Ol Chiki","Orkh":"Chữ Orkhon","Orya":"Chữ Oriya","Osma":"Chữ Osmanya","Palm":"Chữ Palmyrene","Pauc":"Pauc","Perm":"Chữ Permic cổ","Phag":"Chữ Phags-pa","Phli":"Chữ Pahlavi Văn bia","Phlp":"Chữ Pahlavi Thánh ca","Phlv":"Chữ Pahlavi Sách","Phnx":"Chữ Phoenicia","Plrd":"Ngữ âm Pollard","Prti":"Chữ Parthia Văn bia","Qaaa":"Qaaa","Qaab":"Qaab","Qaac":"Qaac","Qaad":"Qaad","Qaae":"Qaae","Qaaf":"Qaaf","Qaag":"Qaag","Qaah":"Qaah","Qaaj":"Qaaj","Qaak":"Qaak","Qaal":"Qaal","Qaam":"Qaam","Qaan":"Qaan","Qaao":"Qaao","Qaap":"Qaap","Qaaq":"Qaaq","Qaar":"Qaar","Qaas":"Qaas","Qaat":"Qaat","Qaau":"Qaau","Qaav":"Qaav","Qaaw":"Qaaw","Qaax":"Qaax","Qaay":"Qaay","Qaaz":"Qaaz","Qaba":"Qaba","Qabb":"Qabb","Qabc":"Qabc","Qabd":"Qabd","Qabe":"Qabe","Qabf":"Qabf","Qabg":"Qabg","Qabh":"Qabh","Qabi":"Qabi","Qabj":"Qabj","Qabk":"Qabk","Qabl":"Qabl","Qabm":"Qabm","Qabn":"Qabn","Qabo":"Qabo","Qabp":"Qabp","Qabq":"Qabq","Qabr":"Qabr","Qabs":"Qabs","Qabt":"Qabt","Qabu":"Qabu","Qabv":"Qabv","Qabw":"Qabw","Qabx":"Qabx","Rjng":"Chữ Rejang","Roro":"Chữ Rongorongo","Runr":"Chữ Runic","Samr":"Chữ Samaritan","Sara":"Chữ Sarati","Sarb":"Chữ Nam Ả Rập cổ","Saur":"Chữ Saurashtra","Sgnw":"Chữ viết Ký hiệu","Shaw":"Chữ Shavian","Shrd":"Chữ Sharada","Sidd":"Sidd","Sind":"Chữ Khudawadi","Sinh":"Chữ Sinhala","Sora":"Chữ Sora Sompeng","Sund":"Chữ Xu-đăng","Sylo":"Chữ Syloti Nagri","Syrc":"Chữ Syria","Syre":"Chữ Estrangelo Syriac","Syrj":"Chữ Tây Syria","Syrn":"Chữ Đông Syria","Tagb":"Chữ Tagbanwa","Takr":"Chữ Takri","Tale":"Chữ Thái Na","Talu":"Chữ Thái Lặc mới","Taml":"Chữ Tamil","Tang":"Chữ Tangut","Tavt":"Chữ Thái Việt","Telu":"Chữ Telugu","Teng":"Chữ Tengwar","Tfng":"Chữ Tifinagh","Tglg":"Chữ Tagalog","Thaa":"Chữ Thaana","Thai":"Chữ Thái","Tibt":"Chữ Tây Tạng","Tirh":"Chữ Tirhuta","Ugar":"Chữ Ugarit","Vaii":"Chữ Vai","Visp":"Tiếng nói Nhìn thấy được","Wara":"Chữ Varang Kshiti","Wole":"Chữ Woleai","Xpeo":"Chữ Ba Tư cổ","Xsux":"Chữ hình nêm Sumero-Akkadian","Yiii":"Chữ Di","Zinh":"Chữ Kế thừa","Zmth":"Ký hiệu Toán học","Zsym":"Ký hiệu","Zxxx":"Chưa có chữ viết","Zyyy":"Chung","Zzzz":"Chữ viết không xác định"},"territories":{"142":"Châu Á","143":"Trung Á","145":"Tây Á","150":"Châu Âu","151":"Đông Âu","154":"Bắc Âu","155":"Tây Âu","419":"Châu Mỹ La-tinh","001":"Thế giới","002":"Châu Phi","003":"Bắc Mỹ","005":"Nam Mỹ","009":"Châu Đại Dương","011":"Tây Phi","013":"Trung Mỹ","014":"Đông Phi","015":"Bắc Phi","017":"Trung Phi","018":"Miền Nam Châu Phi","019":"Châu Mỹ","021":"Miền Bắc Châu Mỹ","029":"Ca-ri-bê","030":"Đông Á","034":"Nam Á","035":"Đông Nam Á","039":"Nam Âu","053":"Úc và New Zealand","054":"Melanesia","057":"Vùng Micronesian","061":"Polynesia","AC":"Đảo Ascension","AD":"Andorra","AE":"Các Tiểu V.quốc Ả Rập T.nhất","AF":"Afghanistan","AG":"Antigua và Barbuda","AI":"Anguilla","AL":"Albani","AM":"Armenia","AN":"Tây Ấn Hà Lan","AO":"Angola","AQ":"Nam Cực","AR":"Argentina","AS":"Đảo Somoa thuộc Mỹ","AT":"Áo","AU":"Úc","AW":"Aruba","AX":"Quần đảo Åland","AZ":"Azerbaijan","BA":"Bosnia và Herzegovina","BB":"Barbados","BD":"Bangladesh","BE":"Bỉ","BF":"Burkina Faso","BG":"Bungari","BH":"Bahrain","BI":"Burundi","BJ":"Benin","BL":"Saint Barthélemy","BM":"Bermuda","BN":"Brunei","BO":"Bolivia","BQ":"Ca-ri-bê Hà Lan","BR":"Brazil","BS":"Bahamas","BT":"Bhutan","BV":"Đảo Bouvet","BW":"Botswana","BY":"Belarus","BZ":"Belize","CA":"Canada","CC":"Quần đảo Cocos (Keeling)","CD":"Congo - Kinshasa","CD-alt-variant":"Cộng hòa Dân chủ Congo","CF":"Cộng hòa Trung Phi","CG":"Congo - Brazzaville","CG-alt-variant":"Cộng hòa Congo","CH":"Thụy Sĩ","CI":"Bờ Biển Ngà","CI-alt-variant":"CI","CK":"Quần đảo Cook","CL":"Chile","CM":"Cameroon","CN":"Trung Quốc","CO":"Colombia","CP":"Đảo Clipperton","CR":"Costa Rica","CU":"Cuba","CV":"Cape Verde","CW":"Curaçao","CX":"Đảo Giáng Sinh","CY":"Síp","CZ":"Cộng hòa Séc","DE":"Đức","DG":"Diego Garcia","DJ":"Djibouti","DK":"Đan Mạch","DM":"Dominica","DO":"Cộng hòa Dominica","DZ":"Algeria","EA":"Ceuta và Melilla","EC":"Ecuador","EE":"Estonia","EG":"Ai Cập","EH":"Tây Sahara","ER":"Eritrea","ES":"Tây Ban Nha","ET":"Ethiopia","EU":"Liên Minh Châu Âu","FI":"Phần Lan","FJ":"Fiji","FK":"Quần đảo Falkland","FK-alt-variant":"Quần đảo Falkland (Islas Malvinas)","FM":"Micronesia","FO":"Quần đảo Faroe","FR":"Pháp","GA":"Gabon","GB":"Vương quốc Anh","GB-alt-short":"Vương quốc Anh","GD":"Grenada","GE":"Georgia","GF":"Guiana thuộc Pháp","GG":"Guernsey","GH":"Ghana","GI":"Gibraltar","GL":"Greenland","GM":"Gambia","GN":"Guinea","GP":"Guadeloupe","GQ":"Guinea Xích Đạo","GR":"Hy Lạp","GS":"Quần đảo Nam Georgia và Nam Sandwich","GT":"Guatemala","GU":"Guam","GW":"Guinea-Bissau","GY":"Guyana","HK":"Đặc khu hành chính Hồng Kông - Trung Quốc","HK-alt-short":"Hồng Kông","HM":"Đảo Heard và Quần đảo McDonald","HN":"Honduras","HR":"Croatia","HT":"Haiti","HU":"Hungari","IC":"Quần đảo Canary","ID":"Indonesia","IE":"Ai-len","IL":"Israel","IM":"Đảo Man","IN":"Ấn Độ","IO":"Thuộc địa Anh tại Ấn Độ Dương","IQ":"I-rắc","IR":"Iran","IS":"Iceland","IT":"Ý","JE":"Jersey","JM":"Jamaica","JO":"Jordan","JP":"Nhật Bản","KE":"Kenya","KG":"Kyrgyzstan","KH":"Campuchia","KI":"Kiribati","KM":"Comoros","KN":"Saint Kitts và Nevis","KP":"Triều Tiên","KR":"Hàn Quốc","KW":"Cô-oét","KY":"Quần đảo Cayman","KZ":"Kazakhstan","LA":"Lào","LB":"Li-băng","LC":"Saint Lucia","LI":"Liechtenstein","LK":"Sri Lanka","LR":"Liberia","LS":"Lesotho","LT":"Lít-va","LU":"Luxembourg","LV":"Latvia","LY":"Li-bi","MA":"Ma-rốc","MC":"Monaco","MD":"Moldova","ME":"Montenegro","MF":"Saint Martin","MG":"Madagascar","MH":"Quần đảo Marshall","MK":"Macedonia","MK-alt-variant":"Macedonia (FYROM)","ML":"Mali","MM":"Myanmar (Miến Điện)","MN":"Mông Cổ","MO":"Đặc khu hành chính Macao - Trung Quốc","MO-alt-short":"Macao","MP":"Quần đảo Bắc Mariana","MQ":"Martinique","MR":"Mauritania","MS":"Montserrat","MT":"Malta","MU":"Mauritius","MV":"Maldives","MW":"Malawi","MX":"Mexico","MY":"Malaysia","MZ":"Mozambique","NA":"Namibia","NC":"New Caledonia","NE":"Niger","NF":"Đảo Norfolk","NG":"Nigeria","NI":"Nicaragua","NL":"Hà Lan","NO":"Na Uy","NP":"Nepal","NR":"Nauru","NU":"Niue","NZ":"New Zealand","OM":"Oman","PA":"Panama","PE":"Peru","PF":"Polynesia thuộc Pháp","PG":"Papua New Guinea","PH":"Philippin","PK":"Pakistan","PL":"Ba Lan","PM":"Saint Pierre và Miquelon","PN":"Quần đảo Pitcairn","PR":"Puerto Rico","PS":"Lãnh thổ Palestine","PS-alt-short":"Palestine","PT":"Bồ Đào Nha","PW":"Palau","PY":"Paraguay","QA":"Qatar","QO":"Vùng xa xôi thuộc Châu Đại Dương","RE":"Réunion","RO":"Romania","RS":"Serbia","RU":"Nga","RW":"Rwanda","SA":"Ả Rập Xê-út","SB":"Quần đảo Solomon","SC":"Seychelles","SD":"Sudan","SE":"Thụy Điển","SG":"Singapore","SH":"Saint Helena","SI":"Slovenia","SJ":"Svalbard và Jan Mayen","SK":"Slovakia","SL":"Sierra Leone","SM":"San Marino","SN":"Senegal","SO":"Somali","SR":"Suriname","SS":"Nam Sudan","ST":"São Tomé và Príncipe","SV":"El Salvador","SX":"Sint Maarten","SY":"Syria","SZ":"Swaziland","TA":"Tristan da Cunha","TC":"Quần đảo Turk và Caicos","TD":"Chad","TF":"Lãnh thổ miền nam nước Pháp","TG":"Togo","TH":"Thái Lan","TJ":"Tajikistan","TK":"Tokelau","TL":"Đông Timor","TL-alt-variant":"TL","TM":"Turkmenistan","TN":"Tunisia","TO":"Tonga","TR":"Thổ Nhĩ Kỳ","TT":"Trinidad và Tobago","TV":"Tuvalu","TW":"Đài Loan","TZ":"Tanzania","UA":"Ukraina","UG":"Uganda","UM":"Các đảo nhỏ xa t.tâm thuộc Mỹ","US":"Hoa Kỳ","US-alt-short":"Hoa Kỳ","UY":"Uruguay","UZ":"Uzbekistan","VA":"Thành Vatican","VC":"Saint Vincent và Grenadines","VE":"Venezuela","VG":"Quần đảo Virgin thuộc Anh","VI":"Quần đảo Virgin thuộc Mỹ","VN":"Việt Nam","VU":"Vanuatu","WF":"Wallis và Futuna","WS":"Samoa","XK":"Kosovo","YE":"Yemen","YT":"Mayotte","ZA":"Nam Phi","ZM":"Zambia","ZW":"Zimbabwe","ZZ":"Vùng không xác định"},"orientation":"left-to-right","ca-gregorian":{"dateFormat-full":"EEEE, 'ngày' dd MMMM 'năm' y","dateFormat-long":"'Ngày' dd 'tháng' MM 'năm' y","dateFormat-medium":"dd-MM-y","dateFormat-short":"dd/MM/y","timeFormat-full":"HH:mm:ss zzzz","timeFormat-long":"HH:mm:ss z","timeFormat-medium":"HH:mm:ss","timeFormat-short":"HH:mm","dateTimeFormat-full":"{0} {1}","dateTimeFormat-long":"{0} {1}","dateTimeFormat-medium":"{0} {1}","dateTimeFormat-short":"{0} {1}","intervalFormatFallback":"{0} - {1}","intervalFormat-H-H":"HH–HH","intervalFormat-Hm-H":"HH:mm-HH:mm","intervalFormat-Hm-m":"HH:mm-HH:mm","intervalFormat-Hmv-H":"HH:mm-HH:mm v","intervalFormat-Hmv-m":"HH:mm-HH:mm v","intervalFormat-Hv-H":"HH–HH v","intervalFormat-M-M":"'Tháng' M - M","intervalFormat-MEd-M":"EEEE, dd/MM - EEEE, dd/MM","intervalFormat-MEd-d":"EEEE, dd/MM - EEEE, dd/MM","intervalFormat-MMM-M":"MMM-MMM","intervalFormat-MMMEd-M":"EEEE, 'ngày' dd 'tháng' M - EEEE, 'ngày' dd 'tháng' M","intervalFormat-MMMEd-d":"EEEE, 'ngày' dd - EEEE, 'ngày' dd 'tháng' M","intervalFormat-MMMd-M":"'Ngày' dd 'tháng' M - 'Ngày' dd 'tháng' M","intervalFormat-MMMd-d":"'Ngày' dd - 'Ngày' dd 'tháng' M","intervalFormat-Md-M":"dd/MM - dd/MM","intervalFormat-Md-d":"dd/MM - dd/MM","intervalFormat-d-d":"'Ngày' dd-dd","intervalFormat-h-a":"h'h' a - h'h' a","intervalFormat-h-h":"h–h a","intervalFormat-hm-a":"h:mm a – h:mm a","intervalFormat-hm-h":"h:mm-h:mm a","intervalFormat-hm-m":"h:mm-h:mm a","intervalFormat-hmv-a":"h:mm a – h:mm a v","intervalFormat-hmv-h":"h:mm-h:mm a v","intervalFormat-hmv-m":"h:mm-h:mm a v","intervalFormat-hv-a":"h'h' a - h'h' a v","intervalFormat-hv-h":"h–h a v","intervalFormat-y-y":"y-y","intervalFormat-yM-M":"MM/y - MM/y","intervalFormat-yM-y":"MM/y - MM/y","intervalFormat-yMEd-M":"EEEE, dd/MM/y - EEEE, dd/MM/y","intervalFormat-yMEd-d":"EEEE, dd/MM/y - EEEE, dd/MM/y","intervalFormat-yMEd-y":"EEEE, dd/MM/y - EEEE, dd/MM/y","intervalFormat-yMMM-M":"'Tháng' M - 'Tháng' M 'năm' y","intervalFormat-yMMM-y":"'Tháng' M 'năm' y - 'Tháng' M 'năm' y","intervalFormat-yMMMEd-M":"E, dd 'tháng' M - E, dd 'tháng' M, y","intervalFormat-yMMMEd-d":"EEEE, 'ngày' dd MMM - EEEE, 'ngày' dd MMM 'năm' y","intervalFormat-yMMMEd-y":"E, dd 'tháng' M, y - E, dd 'tháng' M, y","intervalFormat-yMMMM-M":"MMMM-MMMM 'năm' y","intervalFormat-yMMMM-y":"MMMM y – MMMM y","intervalFormat-yMMMd-M":"'Ngày' dd 'tháng' M - 'Ngày' dd 'tháng' M 'năm' y","intervalFormat-yMMMd-d":"'Ngày' dd - 'Ngày' dd 'tháng' M 'năm' y","intervalFormat-yMMMd-y":"'Ngày' dd 'tháng' M 'năm' y - 'Ngày' dd 'tháng' M 'năm' y","intervalFormat-yMd-M":"dd/MM/y - dd/MM/y","intervalFormat-yMd-d":"dd/MM/y - dd/MM/y","intervalFormat-yMd-y":"dd/MM/y - dd/MM/y","months-format-abbreviated":["thg 1","thg 2","thg 3","thg 4","thg 5","thg 6","thg 7","thg 8","thg 9","thg 10","thg 11","thg 12"],"months-format-narrow":["1","2","3","4","5","6","7","8","9","10","11","12"],"months-format-wide":["tháng 1","tháng 2","tháng 3","tháng 4","tháng 5","tháng 6","tháng 7","tháng 8","tháng 9","tháng 10","tháng 11","tháng 12"],"months-standAlone-abbreviated":["Thg 1","Thg 2","Thg 3","Thg 4","Thg 5","Thg 6","Thg 7","Thg 8","Thg 9","Thg 10","Thg 11","Thg 12"],"months-standAlone-narrow":["1","2","3","4","5","6","7","8","9","10","11","12"],"months-standAlone-wide":["Tháng 1","Tháng 2","Tháng 3","Tháng 4","Tháng 5","Tháng 6","Tháng 7","Tháng 8","Tháng 9","Tháng 10","Tháng 11","Tháng 12"],"days-format-abbreviated":["CN","Th 2","Th 3","Th 4","Th 5","Th 6","Th 7"],"days-format-narrow":["CN","T2","T3","T4","T5","T6","T7"],"days-format-short":["CN","T2","T3","T4","T5","T6","T7"],"days-format-wide":["Chủ Nhật","Thứ Hai","Thứ Ba","Thứ Tư","Thứ Năm","Thứ Sáu","Thứ Bảy"],"days-standAlone-abbreviated":["CN","Th 2","Th 3","Th 4","Th 5","Th 6","Th 7"],"days-standAlone-narrow":["CN","T2","T3","T4","T5","T6","T7"],"days-standAlone-short":["CN","T2","T3","T4","T5","T6","T7"],"days-standAlone-wide":["Chủ Nhật","Thứ Hai","Thứ Ba","Thứ Tư","Thứ Năm","Thứ Sáu","Thứ Bảy"],"quarters-format-abbreviated":["Q1","Q2","Q3","Q4"],"quarters-format-narrow":["1","2","3","4"],"quarters-format-wide":["Quý 1","Quý 2","Quý 3","Quý 4"],"quarters-standAlone-abbreviated":["Q1","Q2","Q3","Q4"],"quarters-standAlone-narrow":["1","2","3","4"],"quarters-standAlone-wide":["Quý 1","Quý 2","Quý 3","Quý 4"],"dayPeriods-format-abbreviated":["SA","CH"],"dayPeriods-format-narrow":["s","c"],"dayPeriods-format-wide":["SA","CH"],"dayPeriods-standAlone-abbreviated":["SA","CH"],"dayPeriods-standAlone-narrow":["s","c"],"dayPeriods-standAlone-wide":["SA","CH"],"era-wide":{"0":"tr. CN","1":"sau CN"},"era-abbreviated":{"0":"tr. CN","1":"sau CN"},"era-narrow":{"0":"tr. CN","1":"sau CN"}},"ca-islamic":{"dateFormat-full":"EEEE, 'ngày' dd MMMM 'năm' y G","dateFormat-long":"'Ngày' dd 'tháng' M 'năm' y G","dateFormat-medium":"dd-MM-y G","dateFormat-short":"dd/MM/y GGGGG","timeFormat-full":"HH:mm:ss zzzz","timeFormat-long":"HH:mm:ss z","timeFormat-medium":"HH:mm:ss","timeFormat-short":"HH:mm","dateTimeFormat-full":"{0} {1}","dateTimeFormat-long":"{0} {1}","dateTimeFormat-medium":"{0} {1}","dateTimeFormat-short":"{0} {1}","intervalFormatFallback":"{0} - {1}","intervalFormat-H-H":"HH'h' - HH'h'","intervalFormat-Hm-H":"HH:mm-HH:mm","intervalFormat-Hm-m":"HH:mm-HH:mm","intervalFormat-Hmv-H":"HH:mm-HH:mm v","intervalFormat-Hmv-m":"HH:mm-HH:mm v","intervalFormat-Hv-H":"HH'h'-HH'h' v","intervalFormat-M-M":"'Tháng' M - 'Tháng' M","intervalFormat-MEd-M":"EEEE, dd/MM - EEEE, dd/MM","intervalFormat-MEd-d":"EEEE, dd/MM - EEEE, dd/MM","intervalFormat-MMM-M":"MMM-MMM","intervalFormat-MMMEd-M":"EEEE, 'ngày' dd 'tháng' M - EEEE, 'ngày' dd 'tháng' M","intervalFormat-MMMEd-d":"EEEE, 'ngày' dd - EEEE, 'ngày' dd 'tháng' M","intervalFormat-MMMd-M":"'Ngày' dd 'tháng' M - 'Ngày' dd 'tháng' M","intervalFormat-MMMd-d":"'Ngày' dd 'tháng' M - 'Ngày' dd 'tháng' M","intervalFormat-Md-M":"dd/MM - dd/MM","intervalFormat-Md-d":"dd/MM - dd/MM","intervalFormat-d-d":"'Ngày' dd-dd","intervalFormat-h-a":"h'h' a - h'h' a","intervalFormat-h-h":"h'h' - h'h' a","intervalFormat-hm-a":"h:mm a – h:mm a","intervalFormat-hm-h":"h:mm-h:mm a","intervalFormat-hm-m":"h:mm-h:mm a","intervalFormat-hmv-a":"h:mm a – h:mm a v","intervalFormat-hmv-h":"h:mm-h:mm a v","intervalFormat-hmv-m":"h:mm-h:mm a v","intervalFormat-hv-a":"h'h' a - h'h' a v","intervalFormat-hv-h":"h'h'-h'h' a v","intervalFormat-y-y":"y-y G","intervalFormat-yM-M":"MM/y - MM/y G","intervalFormat-yM-y":"MM/y - MM/y G","intervalFormat-yMEd-M":"EEEE, dd/MM/y - EEEE, dd/MM/y G","intervalFormat-yMEd-d":"EEEE, dd/MM/y - EEEE, dd/MM/y G","intervalFormat-yMEd-y":"EEEE, dd/MM/y - EEEE, dd/MM/y G","intervalFormat-yMMM-M":"'Tháng' M - 'Tháng' M 'năm' y G","intervalFormat-yMMM-y":"'Tháng' M 'năm' y - 'Tháng' M 'năm' y G","intervalFormat-yMMMEd-M":"E, dd 'tháng' M - E, dd 'tháng' M, y G","intervalFormat-yMMMEd-d":"EEEE, 'ngày' dd MMM - EEEE, 'ngày' dd MMM 'năm' y G","intervalFormat-yMMMEd-y":"E, dd 'tháng' M, y - E, dd 'tháng' M, y G","intervalFormat-yMMMM-M":"MMMM-MMMM y G","intervalFormat-yMMMM-y":"MMMM y – MMMM y G","intervalFormat-yMMMd-M":"'Ngày' dd 'tháng' M - 'Ngày' dd 'tháng' M 'năm' y G","intervalFormat-yMMMd-d":"'Ngày' dd 'tháng' M - 'Ngày' dd 'tháng' M 'năm' y G","intervalFormat-yMMMd-y":"'Ngày' dd 'tháng' M 'năm' y - 'Ngày' dd 'tháng' M 'năm' y G","intervalFormat-yMd-M":"dd/MM/y - dd/MM/y G","intervalFormat-yMd-d":"dd/MM/y - dd/MM/y G","intervalFormat-yMd-y":"dd/MM/y - dd/MM/y G","months-format-abbreviated":["Muh.","Saf.","Rab. I","Rab. II","Jum. I","Jum. II","Raj.","Sha.","Ram.","Shaw.","Dhuʻl-Q.","Dhuʻl-H."],"months-format-narrow":["1","2","3","4","5","6","7","8","9","10","11","12"],"months-format-wide":["Muharram","Safar","Rabiʻ I","Rabiʻ II","Jumada I","Jumada II","Rajab","Shaʻban","Ramadan","Shawwal","Dhuʻl-Qiʻdah","Dhuʻl-Hijjah"],"months-standAlone-abbreviated":["Muh.","Saf.","Rab. I","Rab. II","Jum. I","Jum. II","Raj.","Sha.","Ram.","Shaw.","Dhuʻl-Q.","Dhuʻl-H."],"months-standAlone-narrow":["1","2","3","4","5","6","7","8","9","10","11","12"],"months-standAlone-wide":["Muharram","Safar","Rabiʻ I","Rabiʻ II","Jumada I","Jumada II","Rajab","Shaʻban","Ramadan","Shawwal","Dhuʻl-Qiʻdah","Dhuʻl-Hijjah"],"days-format-abbreviated":["CN","Th 2","Th 3","Th 4","Th 5","Th 6","Th 7"],"days-format-narrow":["CN","T2","T3","T4","T5","T6","T7"],"days-format-short":["CN","T2","T3","T4","T5","T6","T7"],"days-format-wide":["Chủ Nhật","Thứ Hai","Thứ Ba","Thứ Tư","Thứ Năm","Thứ Sáu","Thứ Bảy"],"days-standAlone-abbreviated":["CN","Th 2","Th 3","Th 4","Th 5","Th 6","Th 7"],"days-standAlone-narrow":["CN","T2","T3","T4","T5","T6","T7"],"days-standAlone-short":["CN","T2","T3","T4","T5","T6","T7"],"days-standAlone-wide":["Chủ Nhật","Thứ Hai","Thứ Ba","Thứ Tư","Thứ Năm","Thứ Sáu","Thứ Bảy"],"quarters-format-abbreviated":["Q1","Q2","Q3","Q4"],"quarters-format-narrow":["1","2","3","4"],"quarters-format-wide":["Quý 1","Quý 2","Quý 3","Quý 4"],"quarters-standAlone-abbreviated":["Q1","Q2","Q3","Q4"],"quarters-standAlone-narrow":["1","2","3","4"],"quarters-standAlone-wide":["Quý 1","Quý 2","Quý 3","Quý 4"],"dayPeriods-format-abbreviated":["SA","CH"],"dayPeriods-format-narrow":["s","c"],"dayPeriods-format-wide":["SA","CH"],"dayPeriods-standAlone-abbreviated":["SA","CH"],"dayPeriods-standAlone-narrow":["s","c"],"dayPeriods-standAlone-wide":["SA","CH"],"era-wide":{"0":"AH"},"era-abbreviated":{"0":"AH"},"era-narrow":{"0":"AH"}},"dateField-year-displayName":"Năm","dateField-year-relative--1":"năm ngoái","dateField-year-relative-0":"năm nay","dateField-year-relative-1":"năm sau","dateField-year-relative-future-other":"trong {0} năm nữa","dateField-year-relative-past-other":"{0} năm trước","dateField-month-displayName":"Tháng","dateField-month-relative--1":"tháng trước","dateField-month-relative-0":"tháng này","dateField-month-relative-1":"tháng sau","dateField-month-relative-future-other":"trong {0} tháng nữa","dateField-month-relative-past-other":"{0} tháng trước","dateField-week-displayName":"Tuần","dateField-week-relative--1":"tuần trước","dateField-week-relative-0":"tuần này","dateField-week-relative-1":"tuần sau","dateField-week-relative-future-other":"trong {0} tuần nữa","dateField-week-relative-past-other":"{0} tuần trước","dateField-day-displayName":"Ngày","dateField-day-relative--1":"hôm qua","dateField-day-relative-0":"hôm nay","dateField-day-relative-1":"ngày mai","dateField-day-relative-future-other":"trong {0} ngày nữa","dateField-day-relative-past-other":"{0} ngày trước","dateField-hour-displayName":"Giờ","dateField-hour-relative-future-other":"trong {0} giờ nữa","dateField-hour-relative-past-other":"{0} giờ trước","dateField-minute-displayName":"Phút","dateField-minute-relative-future-other":"trong {0} phút nữa","dateField-minute-relative-past-other":"{0} phút trước","dateField-second-displayName":"Giây","dateField-second-relative-0":"bây giờ","dateField-second-relative-future-other":"trong {0} giây nữa","dateField-second-relative-past-other":"{0} giây trước","decimalFormat":{"standard":"#,##0.###"},"decimalFormat-long":{"1000-other":"0 nghìn","10000-other":"00 nghìn","100000-other":"000 nghìn","1000000-other":"0 triệu","10000000-other":"00 triệu","100000000-other":"000 triệu","1000000000-other":"0 tỷ","10000000000-other":"00 tỷ","100000000000-other":"000 tỷ","1000000000000-other":"0 nghìn tỷ","10000000000000-other":"00 nghìn tỷ","100000000000000-other":"000 nghìn tỷ"},"decimalFormat-short":{"1000-other":"0 N","10000-other":"00 N","100000-other":"000 N","1000000-other":"0 Tr","10000000-other":"00 Tr","100000000-other":"000 Tr","1000000000-other":"0 T","10000000000-other":"00 T","100000000000-other":"000 T","1000000000000-other":"0 NT","10000000000000-other":"00 NT","100000000000000-other":"000 NT"},"scientificFormat":{"standard":"#E0"},"percentFormat":{"standard":"#,##0%"},"currencyFormat":{"standard":"#,##0.00 ¤","accounting":"#,##0.00 ¤"},"symbols-latn-decimal":",","symbols-latn-group":".","symbols-latn-list":";","symbols-latn-percentSign":"%","symbols-latn-plusSign":"+","symbols-latn-minusSign":"-","symbols-latn-exponential":"E","symbols-latn-superscriptingExponent":"×","symbols-latn-perMille":"‰","symbols-latn-infinity":"∞","symbols-latn-nan":"NaN","symbols-latn-timeSeparator":":","currencySymbols":{"AUD":"AU$","BRL":"R$","CAD":"CA$","CNY":"CN¥","EUR":"€","GBP":"£","HKD":"HK$","ILS":"₪","INR":"₹","JPY":"JP¥","KRW":"₩","MXN":"MX$","NZD":"NZ$","THB":"฿","TWD":"NT$","USD":"US$","VND":"₫","XAF":"FCFA","XCD":"EC$","XOF":"CFA","XPF":"CFPF"},"currencyDigits":{"ADP":0,"AFN":0,"ALL":0,"AMD":0,"BHD":3,"BIF":0,"BYR":0,"CAD":2,"CHF":2,"CLF":4,"CLP":0,"COP":0,"CRC":0,"CZK":2,"DEFAULT":2,"DJF":0,"ESP":0,"GNF":0,"GYD":0,"HUF":2,"IDR":0,"IQD":0,"IRR":0,"ISK":0,"ITL":0,"JOD":3,"JPY":0,"KMF":0,"KPW":0,"KRW":0,"KWD":3,"LAK":0,"LBP":0,"LUF":0,"LYD":3,"MGA":0,"MGF":0,"MMK":0,"MNT":0,"MRO":0,"MUR":0,"OMR":3,"PKR":0,"PYG":0,"RSD":0,"RWF":0,"SLL":0,"SOS":0,"STD":0,"SYP":0,"TMM":0,"TND":3,"TRL":0,"TWD":2,"TZS":0,"UGX":0,"UYI":0,"UZS":0,"VND":0,"VUV":0,"XAF":0,"XOF":0,"XPF":0,"YER":0,"ZMK":0,"ZWD":0},"weekData-minDays":1,"weekData-firstDay":1,"weekData-weekendStart":6,"weekData-weekendEnd":0}