{
    "type": "LazyLoad",
    "config": {},
    "action": "index",
    "instanceId": "yui_3_5_1_2_6_1360479977983_82",
    "appConfig": {
        "mojitsDirs": [
            "mojits"
        ],
        "routesFiles": [
            "routes.json"
        ],
        "tunnelPrefix": "/tunnel",
        "yui": {
            "dependencyCalculations": "precomputed"
        },
        "appPort": 6789,
        "staticHandling": {
            "appName": "todomvc",
            "useRollups": true
        },
        "log": {
            "server": {
                "yui": false,
                "level": "warn"
            },
            "client": {
                "yui": false,
                "level": "warn"
            }
        },
        "builds": {
            "html5app": {
                "forceRelativePaths": true,
                "attachManifest": true
            }
        }
    },
    "models": {},
    "views": {
        "index": {
            "binder-url": "/static/LazyLoad/binders/index.js",
            "binder-path": "/static/LazyLoad/binders/index.js",
            "content-path": "/static/LazyLoad/views/index.hb.html",
            "engine": "hb",
            "binder-module": "LazyLoadBinderIndex",
            "binder-yui-sorted": {
                "yui-base": "http://yui.yahooapis.com/3.5.1-2/build/yui-base/yui-base-min.js",
                "oop": "http://yui.yahooapis.com/3.5.1-2/build/oop/oop-min.js",
                "event-custom-base": "http://yui.yahooapis.com/3.5.1-2/build/event-custom-base/event-custom-base-min.js",
                "intl-base": "http://yui.yahooapis.com/3.5.1-2/build/intl-base/intl-base-min.js",
                "event-custom-complex": "http://yui.yahooapis.com/3.5.1-2/build/event-custom-complex/event-custom-complex-min.js",
                "intl": "http://yui.yahooapis.com/3.5.1-2/build/intl/intl-min.js",
                "querystring-stringify-simple": "http://yui.yahooapis.com/3.5.1-2/build/querystring-stringify-simple/querystring-stringify-simple-min.js",
                "io-base": "http://yui.yahooapis.com/3.5.1-2/build/io-base/io-base-min.js",
                "features": "http://yui.yahooapis.com/3.5.1-2/build/features/features-min.js",
                "dom-core": "http://yui.yahooapis.com/3.5.1-2/build/dom-core/dom-core-min.js",
                "dom-base": "http://yui.yahooapis.com/3.5.1-2/build/dom-base/dom-base-min.js",
                "selector-native": "http://yui.yahooapis.com/3.5.1-2/build/selector-native/selector-native-min.js",
                "selector": "http://yui.yahooapis.com/3.5.1-2/build/selector/selector-min.js",
                "node-core": "http://yui.yahooapis.com/3.5.1-2/build/node-core/node-core-min.js",
                "node-base": "http://yui.yahooapis.com/3.5.1-2/build/node-base/node-base-min.js",
                "event-base": "http://yui.yahooapis.com/3.5.1-2/build/event-base/event-base-min.js",
                "event-delegate": "http://yui.yahooapis.com/3.5.1-2/build/event-delegate/event-delegate-min.js",
                "mojito-perf": "/static/todomvc/rollup.client.js",
                "mojito": "/static/todomvc/rollup.client.js",
                "mojito-logger": "/static/todomvc/rollup.client.js",
                "get": "http://yui.yahooapis.com/3.5.1-2/build/get/get-min.js",
                "mojito-loader": "/static/todomvc/rollup.client.js",
                "mojito-config-addon": "/static/todomvc/rollup.client.js",
                "json-stringify": "http://yui.yahooapis.com/3.5.1-2/build/json-stringify/json-stringify-min.js",
                "mojito-view-renderer": "/static/todomvc/rollup.client.js",
                "array-extras": "http://yui.yahooapis.com/3.5.1-2/build/array-extras/array-extras-min.js",
                "mojito-util": "/static/todomvc/rollup.client.js",
                "mojito-output-adapter-addon": "/static/todomvc/rollup.client.js",
                "querystring-parse": "http://yui.yahooapis.com/3.5.1-2/build/querystring-parse/querystring-parse-min.js",
                "querystring-stringify": "http://yui.yahooapis.com/3.5.1-2/build/querystring-stringify/querystring-stringify-min.js",
                "mojito-route-maker": "/static/todomvc/rollup.client.js",
                "mojito-url-addon": "/static/todomvc/rollup.client.js",
                "mojito-assets-addon": "/static/todomvc/rollup.client.js",
                "cookie": "http://yui.yahooapis.com/3.5.1-2/build/cookie/cookie-min.js",
                "mojito-meta-addon": "/static/todomvc/rollup.client.js",
                "mojito-cookie-addon": "/static/todomvc/rollup.client.js",
                "mojito-params-addon": "/static/todomvc/rollup.client.js",
                "mojito-composite-addon": "/static/todomvc/rollup.client.js",
                "mojito-action-context": "/static/todomvc/rollup.client.js",
                "mojito-controller-context": "/static/todomvc/rollup.client.js",
                "mojito-resource-store-adapter": "/static/todomvc/rollup.client.js",
                "mojito-dispatcher": "/static/todomvc/rollup.client.js",
                "mojito-client-store": "/static/todomvc/rollup.client.js",
                "mojito-mojit-proxy": "/static/todomvc/rollup.client.js",
                "datatype-xml-parse": "http://yui.yahooapis.com/3.5.1-2/build/datatype-xml-parse/datatype-xml-parse-min.js",
                "io-xdr": "http://yui.yahooapis.com/3.5.1-2/build/io-xdr/io-xdr-min.js",
                "io-form": "http://yui.yahooapis.com/3.5.1-2/build/io-form/io-form-min.js",
                "io-upload-iframe": "http://yui.yahooapis.com/3.5.1-2/build/io-upload-iframe/io-upload-iframe-min.js",
                "queue-promote": "http://yui.yahooapis.com/3.5.1-2/build/queue-promote/queue-promote-min.js",
                "io-queue": "http://yui.yahooapis.com/3.5.1-2/build/io-queue/io-queue-min.js",
                "json-parse": "http://yui.yahooapis.com/3.5.1-2/build/json-parse/json-parse-min.js",
                "mojito-tunnel-client": "/static/todomvc/rollup.client.js",
                "node-event-delegate": "http://yui.yahooapis.com/3.5.1-2/build/node-event-delegate/node-event-delegate-min.js",
                "pluginhost-base": "http://yui.yahooapis.com/3.5.1-2/build/pluginhost-base/pluginhost-base-min.js",
                "pluginhost-config": "http://yui.yahooapis.com/3.5.1-2/build/pluginhost-config/pluginhost-config-min.js",
                "node-pluginhost": "http://yui.yahooapis.com/3.5.1-2/build/node-pluginhost/node-pluginhost-min.js",
                "dom-style": "http://yui.yahooapis.com/3.5.1-2/build/dom-style/dom-style-min.js",
                "dom-style-ie": "http://yui.yahooapis.com/3.5.1-2/build/dom-style-ie/dom-style-ie-min.js",
                "dom-screen": "http://yui.yahooapis.com/3.5.1-2/build/dom-screen/dom-screen-min.js",
                "node-screen": "http://yui.yahooapis.com/3.5.1-2/build/node-screen/node-screen-min.js",
                "node-style": "http://yui.yahooapis.com/3.5.1-2/build/node-style/node-style-min.js",
                "mojito-output-handler": "/static/todomvc/rollup.client.js",
                "mojito-client": "/static/todomvc/rollup.client.js",
                "LazyLoadBinderIndex": "/static/LazyLoad/binders/index.js",
                "escape": "http://yui.yahooapis.com/3.5.1-2/build/escape/escape-min.js",
                "handlebars-base": "http://yui.yahooapis.com/3.5.1-2/build/handlebars-base/handlebars-base-min.js",
                "handlebars-compiler": "http://yui.yahooapis.com/3.5.1-2/build/handlebars-compiler/handlebars-compiler-min.js",
                "mojito-hb": "/static/todomvc/rollup.client.js",
                "mojito-mu": "/static/todomvc/rollup.client.js"
            }
        }
    },
    "definition": {},
    "defaults": {},
    "controller-path": "/static/LazyLoad/controller.common.js",
    "assetsRoot": "/static/LazyLoad/assets",
    "yui": {
        "config": {
            "modules": {
                "mojito-analytics-addon": {
                    "requires": [
                        "mojito",
                        "mojito-util",
                        "mojito-meta-addon"
                    ],
                    "fullpath": "/static/todomvc/rollup.client.js"
                },
                "mojito-assets-addon": {
                    "requires": [
                        "mojito",
                        "mojito-util"
                    ],
                    "fullpath": "/static/todomvc/rollup.client.js"
                },
                "mojito-composite-addon": {
                    "requires": [
                        "mojito",
                        "mojito-util",
                        "mojito-params-addon"
                    ],
                    "fullpath": "/static/todomvc/rollup.client.js"
                },
                "mojito-config-addon": {
                    "requires": [
                        "mojito"
                    ],
                    "fullpath": "/static/todomvc/rollup.client.js"
                },
                "mojito-cookie-addon": {
                    "requires": [
                        "cookie",
                        "mojito",
                        "mojito-meta-addon"
                    ],
                    "fullpath": "/static/todomvc/rollup.client.js"
                },
                "mojito-intl-addon": {
                    "requires": [
                        "intl",
                        "datatype-date",
                        "mojito",
                        "mojito-config-addon"
                    ],
                    "fullpath": "/static/todomvc/rollup.client.js"
                },
                "mojito-meta-addon": {
                    "requires": [
                        "mojito-util",
                        "mojito-output-adapter-addon"
                    ],
                    "fullpath": "/static/todomvc/rollup.client.js"
                },
                "mojito-output-adapter-addon": {
                    "requires": [
                        "json-stringify",
                        "event-custom-base",
                        "mojito-view-renderer",
                        "mojito-util",
                        "mojito-perf"
                    ],
                    "fullpath": "/static/todomvc/rollup.client.js"
                },
                "mojito-params-addon": {
                    "requires": [
                        "mojito"
                    ],
                    "fullpath": "/static/todomvc/rollup.client.js"
                },
                "mojito-partial-addon": {
                    "requires": [
                        "mojito-util",
                        "mojito-params-addon",
                        "mojito-view-renderer"
                    ],
                    "fullpath": "/static/todomvc/rollup.client.js"
                },
                "mojito-url-addon": {
                    "requires": [
                        "querystring",
                        "mojito-route-maker",
                        "mojito-util"
                    ],
                    "fullpath": "/static/todomvc/rollup.client.js"
                },
                "mojito-hb": {
                    "requires": [
                        "io-base",
                        "handlebars"
                    ],
                    "fullpath": "/static/todomvc/rollup.client.js"
                },
                "mojito-mu": {
                    "requires": [
                        "mojito-util",
                        "io-base"
                    ],
                    "fullpath": "/static/todomvc/rollup.client.js"
                },
                "mojito-action-context": {
                    "requires": [
                        "mojito-config-addon",
                        "mojito-output-adapter-addon",
                        "mojito-url-addon",
                        "mojito-assets-addon",
                        "mojito-cookie-addon",
                        "mojito-params-addon",
                        "mojito-composite-addon",
                        "mojito-perf"
                    ],
                    "fullpath": "/static/todomvc/rollup.client.js"
                },
                "mojito-controller-context": {
                    "requires": [
                        "mojito-action-context",
                        "mojito-util"
                    ],
                    "fullpath": "/static/todomvc/rollup.client.js"
                },
                "mojito-dispatcher": {
                    "requires": [
                        "mojito-controller-context",
                        "mojito-util",
                        "mojito-resource-store-adapter",
                        "mojito-perf",
                        "intl"
                    ],
                    "fullpath": "/static/todomvc/rollup.client.js"
                },
                "mojito-loader": {
                    "requires": [
                        "get",
                        "mojito"
                    ],
                    "fullpath": "/static/todomvc/rollup.client.js"
                },
                "mojito-logger": {
                    "requires": [
                        "mojito"
                    ],
                    "fullpath": "/static/todomvc/rollup.client.js"
                },
                "mojito-mojit-proxy": {
                    "requires": [
                        "mojito",
                        "mojito-util",
                        "querystring"
                    ],
                    "fullpath": "/static/todomvc/rollup.client.js"
                },
                "mojito-client": {
                    "requires": [
                        "io-base",
                        "event-delegate",
                        "node-base",
                        "querystring-stringify-simple",
                        "mojito",
                        "mojito-logger",
                        "mojito-loader",
                        "mojito-dispatcher",
                        "mojito-route-maker",
                        "mojito-client-store",
                        "mojito-resource-store-adapter",
                        "mojito-mojit-proxy",
                        "mojito-tunnel-client",
                        "mojito-output-handler",
                        "mojito-util"
                    ],
                    "fullpath": "/static/todomvc/rollup.client.js"
                },
                "mojito-test": {
                    "requires": [
                        "mojito"
                    ],
                    "fullpath": "/static/todomvc/rollup.client.js"
                },
                "mojito": {
                    "requires": [
                        "mojito-perf"
                    ],
                    "fullpath": "/static/todomvc/rollup.client.js"
                },
                "mojito-output-handler": {
                    "requires": [
                        "mojito",
                        "json-parse",
                        "node"
                    ],
                    "fullpath": "/static/todomvc/rollup.client.js"
                },
                "mojito-perf": {
                    "requires": [],
                    "fullpath": "/static/todomvc/rollup.client.js"
                },
                "mojito-resource-store-adapter": {
                    "requires": [
                        "mojito-util",
                        "json-stringify"
                    ],
                    "fullpath": "/static/todomvc/rollup.client.js"
                },
                "mojito-rest-lib": {
                    "requires": [
                        "io-base",
                        "querystring-stringify-simple",
                        "mojito"
                    ],
                    "fullpath": "/static/todomvc/rollup.client.js"
                },
                "mojito-route-maker": {
                    "requires": [
                        "querystring-stringify-simple",
                        "querystring-parse",
                        "mojito-util"
                    ],
                    "fullpath": "/static/todomvc/rollup.client.js"
                },
                "mojito-client-store": {
                    "requires": [
                        "mojito-util",
                        "querystring-stringify-simple"
                    ],
                    "fullpath": "/static/todomvc/rollup.client.js"
                },
                "mojito-tunnel-client": {
                    "requires": [
                        "mojito",
                        "io",
                        "json-stringify",
                        "json-parse"
                    ],
                    "fullpath": "/static/todomvc/rollup.client.js"
                },
                "mojito-util": {
                    "requires": [
                        "array-extras",
                        "mojito"
                    ],
                    "fullpath": "/static/todomvc/rollup.client.js"
                },
                "mojito-view-renderer": {
                    "requires": [
                        "mojito"
                    ],
                    "fullpath": "/static/todomvc/rollup.client.js"
                },
                "LazyLoadBinderIndex": {
                    "requires": [
                        "mojito-client",
                        "node",
                        "json"
                    ],
                    "fullpath": "/static/LazyLoad/binders/index.js"
                },
                "LazyLoad": {
                    "requires": [
                        "mojito",
                        "json"
                    ],
                    "fullpath": "/static/LazyLoad/controller.common.js"
                }
            }
        },
        "sorted": [
            "mojito-perf",
            "mojito",
            "yui-base",
            "json-parse",
            "json-stringify",
            "LazyLoad",
            "mojito-config-addon",
            "oop",
            "event-custom-base",
            "mojito-view-renderer",
            "array-extras",
            "mojito-util",
            "mojito-output-adapter-addon",
            "querystring-parse",
            "querystring-stringify",
            "querystring-stringify-simple",
            "mojito-route-maker",
            "mojito-url-addon",
            "mojito-assets-addon",
            "cookie",
            "mojito-meta-addon",
            "mojito-cookie-addon",
            "mojito-params-addon",
            "mojito-composite-addon",
            "mojito-action-context",
            "mojito-controller-context",
            "mojito-resource-store-adapter",
            "intl-base",
            "event-custom-complex",
            "intl",
            "mojito-dispatcher",
            "io-base",
            "io-nodejs",
            "escape",
            "handlebars-base",
            "handlebars-compiler",
            "mojito-hb",
            "mojito-mu"
        ],
        "sortedPaths": {
            "mojito-perf": "/static/todomvc/rollup.client.js",
            "mojito": "/static/todomvc/rollup.client.js",
            "yui-base": "http://yui.yahooapis.com/3.5.1-2/build/yui-base/yui-base-min.js",
            "json-parse": "http://yui.yahooapis.com/3.5.1-2/build/json-parse/json-parse-min.js",
            "json-stringify": "http://yui.yahooapis.com/3.5.1-2/build/json-stringify/json-stringify-min.js",
            "LazyLoad": "/static/LazyLoad/controller.common.js",
            "mojito-config-addon": "/static/todomvc/rollup.client.js",
            "oop": "http://yui.yahooapis.com/3.5.1-2/build/oop/oop-min.js",
            "event-custom-base": "http://yui.yahooapis.com/3.5.1-2/build/event-custom-base/event-custom-base-min.js",
            "mojito-view-renderer": "/static/todomvc/rollup.client.js",
            "array-extras": "http://yui.yahooapis.com/3.5.1-2/build/array-extras/array-extras-min.js",
            "mojito-util": "/static/todomvc/rollup.client.js",
            "mojito-output-adapter-addon": "/static/todomvc/rollup.client.js",
            "querystring-parse": "http://yui.yahooapis.com/3.5.1-2/build/querystring-parse/querystring-parse-min.js",
            "querystring-stringify": "http://yui.yahooapis.com/3.5.1-2/build/querystring-stringify/querystring-stringify-min.js",
            "querystring-stringify-simple": "http://yui.yahooapis.com/3.5.1-2/build/querystring-stringify-simple/querystring-stringify-simple-min.js",
            "mojito-route-maker": "/static/todomvc/rollup.client.js",
            "mojito-url-addon": "/static/todomvc/rollup.client.js",
            "mojito-assets-addon": "/static/todomvc/rollup.client.js",
            "cookie": "http://yui.yahooapis.com/3.5.1-2/build/cookie/cookie-min.js",
            "mojito-meta-addon": "/static/todomvc/rollup.client.js",
            "mojito-cookie-addon": "/static/todomvc/rollup.client.js",
            "mojito-params-addon": "/static/todomvc/rollup.client.js",
            "mojito-composite-addon": "/static/todomvc/rollup.client.js",
            "mojito-action-context": "/static/todomvc/rollup.client.js",
            "mojito-controller-context": "/static/todomvc/rollup.client.js",
            "mojito-resource-store-adapter": "/static/todomvc/rollup.client.js",
            "intl-base": "http://yui.yahooapis.com/3.5.1-2/build/intl-base/intl-base-min.js",
            "event-custom-complex": "http://yui.yahooapis.com/3.5.1-2/build/event-custom-complex/event-custom-complex-min.js",
            "intl": "http://yui.yahooapis.com/3.5.1-2/build/intl/intl-min.js",
            "mojito-dispatcher": "/static/todomvc/rollup.client.js",
            "io-base": "http://yui.yahooapis.com/3.5.1-2/build/io-base/io-base-min.js",
            "escape": "http://yui.yahooapis.com/3.5.1-2/build/escape/escape-min.js",
            "handlebars-base": "http://yui.yahooapis.com/3.5.1-2/build/handlebars-base/handlebars-base-min.js",
            "handlebars-compiler": "http://yui.yahooapis.com/3.5.1-2/build/handlebars-compiler/handlebars-compiler-min.js",
            "mojito-hb": "/static/todomvc/rollup.client.js",
            "mojito-mu": "/static/todomvc/rollup.client.js"
        }
    },
    "controller-module": "LazyLoad"
}